activecollab_digger/__init__.py
activecollab_digger/activecollab.py
activecollab_digger/apps.py
activecollab_digger/context_processors.py
activecollab_digger/tests.py
activecollab_digger/urls.py
activecollab_digger/views.py
activecollab_digger/static/activecollab_digger/css/app.css
activecollab_digger/static/activecollab_digger/js/app.js
activecollab_digger/static/vendor/bulma/css/bulma.css
activecollab_digger/static/vendor/bulma/css/bulma.css.map
activecollab_digger/static/vendor/font-awesome/css/font-awesome.min.css
activecollab_digger/static/vendor/font-awesome/fonts/FontAwesome.otf
activecollab_digger/static/vendor/font-awesome/fonts/fontawesome-webfont.eot
activecollab_digger/static/vendor/font-awesome/fonts/fontawesome-webfont.svg
activecollab_digger/static/vendor/font-awesome/fonts/fontawesome-webfont.ttf
activecollab_digger/static/vendor/font-awesome/fonts/fontawesome-webfont.woff
activecollab_digger/static/vendor/font-awesome/fonts/fontawesome-webfont.woff2
activecollab_digger/static/vendor/vue/dist/vue.min.js
activecollab_digger/templates/activecollab_digger/index.html
django_activecollab_digger-0.7.2.dist-info/DESCRIPTION.rst
django_activecollab_digger-0.7.2.dist-info/METADATA
django_activecollab_digger-0.7.2.dist-info/RECORD
django_activecollab_digger-0.7.2.dist-info/WHEEL
django_activecollab_digger-0.7.2.dist-info/metadata.json
django_activecollab_digger-0.7.2.dist-info/top_level.txt
