Metadata-Version: 2.0
Name: django-activecollab-digger
Version: 0.7.2
Summary: Django ActiveCollab application
Home-page: https://github.com/kingsdigitallab/django-activecollab-digger
Author: King's Digital Lab
Author-email: kdl-info@kcl.ac.uk
License: MIT
Keywords: django activecollab
Platform: UNKNOWN
Classifier: Development Status :: 4 - Beta
Classifier: Framework :: Django
Classifier: Intended Audience :: Developers
Classifier: License :: OSI Approved :: MIT License
Classifier: Programming Language :: Python :: 2
Classifier: Programming Language :: Python :: 2.7
Classifier: Programming Language :: Python :: 3
Classifier: Programming Language :: Python :: 3.3
Classifier: Programming Language :: Python :: 3.4
Classifier: Programming Language :: Python :: 3.5
Classifier: Topic :: Utilities
Requires-Dist: requests[security]
Requires-Dist: simplejson
